ai_agent_marketplace/__init__.py
ai_agent_marketplace/base.py
ai_agent_marketplace/cli.py
ai_agent_marketplace/config.py
ai_agent_marketplace/constants.py
ai_agent_marketplace/utils.py
ai_agent_marketplace/data/__init__.py
ai_agent_marketplace/data/add_service_api_demo.json
ai_agent_marketplace/data/schema.json
ai_agent_marketplace/data/search_api_demo.json
ai_agent_marketplace/v1/__init__.py
ai_agent_marketplace/v1/base.py
ai_agent_marketplace/v1/utils.py
ai_agent_marketplace-0.0.6.dist-info/METADATA
ai_agent_marketplace-0.0.6.dist-info/WHEEL
ai_agent_marketplace-0.0.6.dist-info/entry_points.txt
ai_agent_marketplace-0.0.6.dist-info/top_level.txt
ai_agent_marketplace-0.0.6.dist-info/RECORD
