Metadata-Version: 2.4
Name: ai_agent_marketplace
Version: 0.0.6
Summary: AI Agent Marketplace Registry | AI Agent Directory | AI Agent Index Repo | AI Agent Search Engine for Public Available AI Agents Community
Author-email: aihubadmin@126.com
License: MIT License
Project-URL: Homepage, https://www.deepnlp.org/store/ai-agent
Project-URL: Repository, https://github.com/aiagenta2z/ai-agent-marketplace
Keywords: AI Agent Marketplace,AI Agent Registry,AI Agent API,AI Agent,MCP SERVER
Classifier: Development Status :: 3 - Alpha
Classifier: Intended Audience :: Developers
Classifier: Topic :: Software Development :: Build Tools
Classifier: License :: OSI Approved :: MIT License
Requires-Python: >=3.4
Requires-Dist: requests>=2.17.0
Dynamic: requires-python
